bestpy/__init__.py
bestpy/answers.py
bestpy/best_class.py
bestpy-0.1.0.dist-info/LICENSE
bestpy-0.1.0.dist-info/WHEEL
bestpy-0.1.0.dist-info/METADATA
bestpy-0.1.0.dist-info/RECORD
