Metadata-Version: 2.1
Name: bestpy
Version: 0.1.0
Summary: A package to find out what's best
Home-page: https://github.com/gustavwilliam/bestpy
License: MIT
Author: Gustav Odinger
Requires-Python: >=3.8,<4.0
Classifier: License :: OSI Approved :: MIT License
Classifier: Programming Language :: Python :: 3
Classifier: Programming Language :: Python :: 3.8
Project-URL: Repository, https://github.com/gustavwilliam/bestpy
